transpeg/__init__.py
transpeg/__main__.py
transpeg/__version__.py
transpeg/main.py
transpeg-1.2.0.dist-info/LICENSE
transpeg-1.2.0.dist-info/METADATA
transpeg-1.2.0.dist-info/WHEEL
transpeg-1.2.0.dist-info/entry_points.txt
transpeg-1.2.0.dist-info/top_level.txt
transpeg-1.2.0.dist-info/RECORD
