Metadata-Version: 2.1
Name: transpeg
Version: 1.2.0
Summary: Transparent JPEG emulation via SVG
Home-page: https://github.com/igrmk/transpeg
Author: igrmk
Author-email: igrmkx@gmail.com
License: UNKNOWN
Platform: UNKNOWN
Classifier: Programming Language :: Python :: 3
Classifier: License :: OSI Approved :: MIT License
Classifier: Operating System :: OS Independent
Requires-Python: >=3.0
Requires-Dist: pillow (>=7.0.0)
Requires-Dist: svgwrite (>=1.4)
Requires-Dist: importlib-metadata ; python_version < "3.8"
